GraphRetrieval/GraphRetrieval.py
GraphRetrieval/__init__.py
GraphRetrieval-0.2.2.dist-info/METADATA
GraphRetrieval-0.2.2.dist-info/WHEEL
GraphRetrieval-0.2.2.dist-info/top_level.txt
GraphRetrieval-0.2.2.dist-info/RECORD
